Metadata-Version: 2.1
Name: odoo12-addon-shopinvader
Version: 12.0.3.17.4
Summary: Shopinvader
Home-page: https://github.com/shopinvader/odoo-shopinvader
Author: Akretion
License: AGPL-3
Platform: UNKNOWN
Classifier: Programming Language :: Python
Classifier: Framework :: Odoo
Classifier: License :: OSI Approved :: GNU Affero General Public License v3
Requires-Python: >=3.5
Requires-Dist: cerberus
Requires-Dist: odoo12-addon-auth-api-key
Requires-Dist: odoo12-addon-base-jsonify
Requires-Dist: odoo12-addon-base-rest
Requires-Dist: odoo12-addon-base-sparse-field-list-support
Requires-Dist: odoo12-addon-base-suspend-security
Requires-Dist: odoo12-addon-base-url
Requires-Dist: odoo12-addon-component-event
Requires-Dist: odoo12-addon-onchange-helper
Requires-Dist: odoo12-addon-queue-job
Requires-Dist: odoo12-addon-sale-discount-display-amount
Requires-Dist: odoo12-addon-sale-order-price-recalculation
Requires-Dist: odoo (<12.1dev,>=12.0a)
Requires-Dist: openupgradelib
Requires-Dist: unidecode
